CHANGELOG.md
CONTRIBUTING.md
LICENSE.md
README.md
RELEASE.md
oliver/__init__.py
oliver/__main__.py
oliver/integrations/__init__.py
oliver/integrations/aws/__init__.py
oliver/integrations/aws/aggregate.py
oliver/integrations/aws/clean.py
oliver/integrations/aws/debug.py
oliver/integrations/azure/__init__.py
oliver/integrations/azure/aggregate.py
oliver/integrations/azure/cosmos.py
oliver/lib/__init__.py
oliver/lib/api.py
oliver/lib/args.py
oliver/lib/batch.py
oliver/lib/config.py
oliver/lib/constants.py
oliver/lib/errors.py
oliver/lib/oliver.py
oliver/lib/parsing.py
oliver/lib/reporting.py
oliver/lib/utils.py
oliver/lib/workflows.py
oliver/subcommands/__init__.py
oliver/subcommands/__template__.py
oliver/subcommands/abort.py
oliver/subcommands/aggregate.py
oliver/subcommands/aws.py
oliver/subcommands/azure.py
oliver/subcommands/batches.py
oliver/subcommands/config.py
oliver/subcommands/configure.py
oliver/subcommands/inputs.py
oliver/subcommands/inspect.py
oliver/subcommands/logs.py
oliver/subcommands/outputs.py
oliver/subcommands/retry.py
oliver/subcommands/runtime.py
oliver/subcommands/status.py
oliver/subcommands/submit.py
stjudecloud_oliver-1.4.11.dist-info/entry_points.txt
stjudecloud_oliver-1.4.11.dist-info/LICENSE.md
stjudecloud_oliver-1.4.11.dist-info/WHEEL
stjudecloud_oliver-1.4.11.dist-info/METADATA
stjudecloud_oliver-1.4.11.dist-info/RECORD
