Metadata-Version: 2.1
Name: stjudecloud-oliver
Version: 1.4.11
Summary: An opinionated Cromwell orchestration system
Home-page: https://stjudecloud.github.io/oliver/
License: MIT
Keywords: bioinformatics,genomics,workflows,cromwell
Author: Clay Mcleod
Author-email: clay.mcleod@STJUDE.org
Requires-Python: >=3.9.7,<4.0.0
Classifier: Development Status :: 5 - Production/Stable
Classifier: License :: OSI Approved :: MIT License
Classifier: Operating System :: OS Independent
Classifier: Programming Language :: Python :: 3
Classifier: Programming Language :: Python :: 3.10
Classifier: Programming Language :: Python :: 3
Classifier: Topic :: Scientific/Engineering :: Bio-Informatics
Requires-Dist: aiohttp (>=3.6.2,<4.0.0)
Requires-Dist: azure-cosmos (>=3.1.2,<5.0.0)
Requires-Dist: boto3 (>=1.11.9,<2.0.0)
Requires-Dist: logzero (>=1.5.0,<2.0.0)
Requires-Dist: mypy-boto3[batch,logs] (>=1.12.17,<2.0.0)
Requires-Dist: mypy_boto3_batch (>=1.12.21,<2.0.0)
Requires-Dist: mypy_boto3_logs (>=1.12.21,<2.0.0)
Requires-Dist: pendulum (>=2.0.5,<3.0.0)
Requires-Dist: requests (>=2.22.0,<3.0.0)
Requires-Dist: tabulate (>=0.8.6,<0.9.0)
Requires-Dist: typed-ast (==1.5.2)
Requires-Dist: tzlocal (<3.0.0)
Project-URL: Documentation, https://stjudecloud.github.io/oliver/
Project-URL: Repository, https://github.com/stjudecloud/oliver
